mcp_factory/__init__.py
mcp_factory/exceptions.py
mcp_factory/factory.py
mcp_factory/middleware.py
mcp_factory/adapters/__init__.py
mcp_factory/adapters/async_utils.py
mcp_factory/adapters/base.py
mcp_factory/adapters/cache.py
mcp_factory/adapters/cli_adapter.py
mcp_factory/adapters/http_adapter.py
mcp_factory/adapters/multi_adapter.py
mcp_factory/adapters/python_adapter.py
mcp_factory/authorization/__init__.py
mcp_factory/authorization/audit.py
mcp_factory/authorization/cache.py
mcp_factory/authorization/config.py
mcp_factory/authorization/debug_service.py
mcp_factory/authorization/manager.py
mcp_factory/authorization/models.py
mcp_factory/authorization/permission_engine.py
mcp_factory/authorization/rbac_model.conf
mcp_factory/authorization/role_service.py
mcp_factory/authorization/saas_service.py
mcp_factory/billing/__init__.py
mcp_factory/billing/manager.py
mcp_factory/billing/models.py
mcp_factory/billing/system.py
mcp_factory/billing/engines/__init__.py
mcp_factory/billing/engines/lago.py
mcp_factory/billing/gateways/__init__.py
mcp_factory/billing/gateways/custom.py
mcp_factory/billing/gateways/local.py
mcp_factory/billing/gateways/stripe.py
mcp_factory/cli/__init__.py
mcp_factory/cli/error_filter.py
mcp_factory/cli/helpers.py
mcp_factory/cli/main.py
mcp_factory/config/__init__.py
mcp_factory/config/manager.py
mcp_factory/config/schema.py
mcp_factory/mounting/__init__.py
mcp_factory/mounting/models.py
mcp_factory/mounting/mounter.py
mcp_factory/mounting/registry.py
mcp_factory/project/__init__.py
mcp_factory/project/builder.py
mcp_factory/project/components.py
mcp_factory/project/constants.py
mcp_factory/project/publisher.py
mcp_factory/project/template.py
mcp_factory/project/validator.py
mcp_factory/server/__init__.py
mcp_factory/server/billing_auth_integration.py
mcp_factory/server/managed_server.py
mcp_factory/server/tool_configs.py
mcp_factory-1.6.3.dist-info/METADATA
mcp_factory-1.6.3.dist-info/WHEEL
mcp_factory-1.6.3.dist-info/entry_points.txt
mcp_factory-1.6.3.dist-info/licenses/LICENSE
mcp_factory-1.6.3.dist-info/RECORD
