Metadata-Version: 2.4
Name: mcp-factory
Version: 1.6.3
Summary: A lightweight factory framework for creating and managing MCP (Model Context Protocol) servers with simplified configuration and project building capabilities.
Project-URL: Homepage, https://github.com/ACNet-AI/mcp-factory
Project-URL: Repository, https://github.com/ACNet-AI/mcp-factory
Project-URL: Bug Tracker, https://github.com/ACNet-AI/mcp-factory/issues
Author-email: ACNet-AI <agencollabnet@gmail.com>
License-Expression: Apache-2.0
License-File: LICENSE
Keywords: ai,factory,management,mcp,model-context-protocol,server
Classifier: Development Status :: 4 - Beta
Classifier: Intended Audience :: Developers
Classifier: Operating System :: OS Independent
Classifier: Programming Language :: Python :: 3
Classifier: Programming Language :: Python :: 3.10
Classifier: Programming Language :: Python :: 3.11
Classifier: Programming Language :: Python :: 3.12
Classifier: Programming Language :: Python :: 3.13
Classifier: Topic :: Internet :: WWW/HTTP :: HTTP Servers
Classifier: Topic :: Scientific/Engineering :: Artificial Intelligence
Classifier: Topic :: Software Development :: Libraries :: Python Modules
Requires-Python: >=3.10
Requires-Dist: aiohttp>=3.12.0
Requires-Dist: casbin>=1.43.0
Requires-Dist: click>=8.2.0
Requires-Dist: cryptography>=45.0.6
Requires-Dist: fastmcp>=2.12.0
Requires-Dist: httpx>=0.28.1
Requires-Dist: jsonschema>=4.24.0
Requires-Dist: lago-python-client>=1.33.1
Requires-Dist: psutil>=7.0.0
Requires-Dist: pydantic>=2.11.0
Requires-Dist: python-dotenv>=1.1.0
Requires-Dist: pyyaml>=6.0
Requires-Dist: questionary>=2.0.1
Requires-Dist: requests>=2.32.0
Requires-Dist: rich>=13.0.0
Requires-Dist: tabulate>=0.9.0
Requires-Dist: toml>=0.10.0
Requires-Dist: uvicorn>=0.34.0
Provides-Extra: billing-full
Requires-Dist: stripe>=10.0.0; extra == 'billing-full'
Provides-Extra: stripe
Requires-Dist: stripe>=10.0.0; extra == 'stripe'
